README
setup.py
./creditcard/__init__.py
./creditcard/internal.py
./creditcard/data/registry.xml
creditcard.egg-info/PKG-INFO
creditcard.egg-info/SOURCES.txt
creditcard.egg-info/dependency_links.txt
creditcard.egg-info/top_level.txt