Metadata-Version: 1.0
Name: creditcard
Version: 1.0.1
Summary: A simple class for identifying, validating, and formatting credit card information
Home-page: https://github.com/alexforster/creditcard
Author: Alex Forster
Author-email: alex@alexforster.com
License: UNKNOWN
Platform: UNKNOWN
